Metadata-Version: 2.1
Name: dms-variants
Version: 1.5.0
Summary: Analyze deep mutational scanning of barcoded variants.
Home-page: https://github.com/jbloomlab/dms_variants
Download-URL: https://github.com/jbloomlab/dms_variants/tarball/1.5.0
Author: `the Bloom lab <https://research.fhcrc.org/bloom/en.html>`_
Author-email: jbloom@fredhutch.org
License: GPLv3
Platform: Linux and Mac OS X.
License-File: LICENSE.txt
Requires-Dist: binarymap>=0.1
Requires-Dist: biopython>=1.73
Requires-Dist: matplotlib>=3.1
Requires-Dist: pandas>=1.2
Requires-Dist: pyarrow
Requires-Dist: plotnine>0.7.0
Requires-Dist: regex>=2.4.153
Requires-Dist: requests
Requires-Dist: scipy>=1.1.0
